php_serialize/__init__.py
php_serialize/py.typed
serialize_php-0.0.4.dist-info/licenses/LICENSE
serialize_php-0.0.4.dist-info/WHEEL
serialize_php-0.0.4.dist-info/METADATA
serialize_php-0.0.4.dist-info/RECORD
