Metadata-Version: 2.4
Name: serialize-php
Version: 0.0.4
Summary: handle contents of serialize/deserialize in php
Keywords: bencode,bittorrent,bit-torrent,serialize,deserialize,p2p
Author-email: trim21 <trim21me@gmail.com>
Requires-Python: >=3.9,<4.0
Classifier: Development Status :: 3 - Alpha
Classifier: License :: OSI Approved :: MIT License
Classifier: Operating System :: OS Independent
Classifier: Programming Language :: Python
Classifier: Programming Language :: Python :: 3 :: Only
License-File: LICENSE
Requires-Dist: typing-extensions>=4.12.2
Project-URL: Homepage, https://github.com/trim21/php-serialize-py
Project-URL: Issues, https://github.com/trim21/php-serialize-py/issues
Project-URL: Repository, https://github.com/trim21/php-serialize-py
